lca_modeller/__init__.py
lca_modeller/gui/__init__.py
lca_modeller/gui/plots.py
lca_modeller/helpers.py
lca_modeller/io/__init__.py
lca_modeller/io/configuration.py
lca_modeller/io/resources/__init__.py
lca_modeller/io/resources/configuration.json
lca_modeller/io/tests/__init__.py
lca_modeller/notebook/data/advanced_example.yaml
lca_modeller/notebook/data/basic_example.yaml
lca_modeller/notebook/data/basic_example_split_impacts.yaml
lca_modeller/notebook/data/custom_lcia_methods.yaml
lca_modeller/notebook/data/lcia_gwp100_custom.csv
lca_modeller/notebook/data/metadata_example.yaml
lca_modeller/notebook/data/prospective_lca.yaml
lca_modeller/notebook/tutorial-notebook.ipynb
lca_modeller-0.0.0.dist-info/METADATA
lca_modeller-0.0.0.dist-info/WHEEL
lca_modeller-0.0.0.dist-info/RECORD
