Metadata-Version: 2.1
Name: lca-modeller
Version: 0.0.0
Summary: Python library to build parametric LCA models from a configuration file. 
License: GPL-3.0-only
Keywords: life cycle assessment,LCA,parametric model,prospective LCA
Author: Félix POLLET
Author-email: felix.pollet@isae-supaero.fr
Requires-Python: >=3.10,<3.12
Classifier: License :: OSI Approved :: GNU General Public License v3 (GPLv3)
Classifier: Programming Language :: Python :: 3
Classifier: Programming Language :: Python :: 3.10
Classifier: Programming Language :: Python :: 3.11
Requires-Dist: bw2calc (>=1.8.2,<2.0.0)
Requires-Dist: bw2data (>=3.6.6,<4.0.0)
Requires-Dist: bw2io (>=0.8.12,<0.9.0)
Requires-Dist: eight (>=1.0.1,<2.0.0) ; sys_platform == "darwin"
Requires-Dist: ensure (>=1.0.0,<2.0.0)
Requires-Dist: intel-openmp (==2023.2.0) ; sys_platform == "darwin"
Requires-Dist: jupyterlab
Requires-Dist: lca-algebraic (>=1.2,<2.0)
Requires-Dist: matplotlib (>=3.7,<4.0)
Requires-Dist: mkl (==2023.2.2) ; sys_platform == "darwin"
Requires-Dist: premise (>=2.2.3,<3.0.0)
Requires-Dist: pyvis (>=0.3.0,<0.4.0)
Requires-Dist: ruamel.yaml (>=0.15,<0.19)
Requires-Dist: tbb (==2021.10.0) ; sys_platform == "darwin"
